binarybotapi/__init__.py
binarybotapi/api.py
binarybotapi/constants.py
binarybotapi/country_id.py
binarybotapi/expiration.py
binarybotapi/global_value.py
binarybotapi/stable_api.py
binarybotapi/http/__init__.py
binarybotapi/http/appinit.py
binarybotapi/http/auth.py
binarybotapi/http/billing.py
binarybotapi/http/buyback.py
binarybotapi/http/changebalance.py
binarybotapi/http/events.py
binarybotapi/http/getprofile.py
binarybotapi/http/getregdata.py
binarybotapi/http/login.py
binarybotapi/http/login2fa.py
binarybotapi/http/loginv2.py
binarybotapi/http/logout.py
binarybotapi/http/profile.py
binarybotapi/http/register.py
binarybotapi/http/resource.py
binarybotapi/http/send_sms.py
binarybotapi/http/token.py
binarybotapi/http/verify.py
binarybotapi/ws/__init__.py
binarybotapi/ws/client.py
binarybotapi/ws/chanels/__init__.py
binarybotapi/ws/chanels/api_game_betinfo.py
binarybotapi/ws/chanels/api_game_getoptions.py
binarybotapi/ws/chanels/base.py
binarybotapi/ws/chanels/buy_place_order_temp.py
binarybotapi/ws/chanels/buyback.py
binarybotapi/ws/chanels/buyv2.py
binarybotapi/ws/chanels/buyv3.py
binarybotapi/ws/chanels/cancel_order.py
binarybotapi/ws/chanels/candles.py
binarybotapi/ws/chanels/change_auto_margin_call.py
binarybotapi/ws/chanels/change_tpsl.py
binarybotapi/ws/chanels/changebalance.py
binarybotapi/ws/chanels/close_position.py
binarybotapi/ws/chanels/digital_option.py
binarybotapi/ws/chanels/get_available_leverages.py
binarybotapi/ws/chanels/get_balances.py
binarybotapi/ws/chanels/get_deferred_orders.py
binarybotapi/ws/chanels/get_financial_information.py
binarybotapi/ws/chanels/get_order.py
binarybotapi/ws/chanels/get_overnight_fee.py
binarybotapi/ws/chanels/get_positions.py
binarybotapi/ws/chanels/heartbeat.py
binarybotapi/ws/chanels/instruments.py
binarybotapi/ws/chanels/leaderboard.py
binarybotapi/ws/chanels/sell_digital_option.py
binarybotapi/ws/chanels/sell_option.py
binarybotapi/ws/chanels/setactives.py
binarybotapi/ws/chanels/ssid.py
binarybotapi-0.1.2.dist-info/METADATA
binarybotapi-0.1.2.dist-info/WHEEL
binarybotapi-0.1.2.dist-info/top_level.txt
binarybotapi-0.1.2.dist-info/RECORD
