Metadata-Version: 2.1
Name: binarybotapi
Version: 0.1.2
Summary: Binary Option API for IQOption in python
Home-page: https://github.com/vish4mi/binarybotapi
Author: Vishal Bhadade
Author-email: vishal.bhadade@gmail.com
Classifier: Programming Language :: Python :: 3
Classifier: License :: OSI Approved :: MIT License
Classifier: Operating System :: OS Independent
Requires-Python: >=3.7
Requires-Dist: pylint
Requires-Dist: requests
Requires-Dist: websocket-client
